.coveragerc
.mailmap
.testr.conf
.travis.yml
AUTHORS
ChangeLog
HACKING.rst
LICENSE
MANIFEST.in
README.rst
babel.cfg
openstack-common.conf
requirements.txt
run_tests.sh
setup.cfg
setup.py
test-requirements.txt
tox.ini
arsenal/__init__.py
arsenal/version.py
arsenal/cmd/__init__.py
arsenal/cmd/director.py
arsenal/common/__init__.py
arsenal/common/config.py
arsenal/common/exception.py
arsenal/common/rate_limiter.py
arsenal/common/service.py
arsenal/common/util.py
arsenal/director/__init__.py
arsenal/director/devstack_scout.py
arsenal/director/onmetal_scout.py
arsenal/director/scheduler.py
arsenal/director/scout.py
arsenal/external/__init__.py
arsenal/external/client_wrapper.py
arsenal/external/glance_client_wrapper.py
arsenal/external/ironic_client_wrapper.py
arsenal/external/nova_client_wrapper.py
arsenal/openstack/__init__.py
arsenal/openstack/common/__init__.py
arsenal/openstack/common/_i18n.py
arsenal/openstack/common/eventlet_backdoor.py
arsenal/openstack/common/local.py
arsenal/openstack/common/log.py
arsenal/openstack/common/loopingcall.py
arsenal/openstack/common/periodic_task.py
arsenal/openstack/common/service.py
arsenal/openstack/common/systemd.py
arsenal/openstack/common/threadgroup.py
arsenal/strategy/__init__.py
arsenal/strategy/base.py
arsenal/strategy/simple_proportional_strategy.py
arsenal/tests/__init__.py
arsenal/tests/base.py
arsenal/tests/test_arsenal.py
arsenal/tests/common/__init__.py
arsenal/tests/common/test_rate_limiter.py
arsenal/tests/director/__init__.py
arsenal/tests/director/test_onmetal_scout.py
arsenal/tests/director/test_scheduler.py
arsenal/tests/external/__init__.py
arsenal/tests/external/ironic_utils.py
arsenal/tests/external/test_client_wrapper.py
arsenal/tests/external/test_glance_client_wrapper.py
arsenal/tests/external/test_ironic_client_wrapper.py
arsenal/tests/external/test_nova_client_wrapper.py
arsenal/tests/strategy/__init__.py
arsenal/tests/strategy/test_simple_proportional_strategy.py
arsenal_director.egg-info/PKG-INFO
arsenal_director.egg-info/SOURCES.txt
arsenal_director.egg-info/dependency_links.txt
arsenal_director.egg-info/entry_points.txt
arsenal_director.egg-info/not-zip-safe
arsenal_director.egg-info/pbr.json
arsenal_director.egg-info/requires.txt
arsenal_director.egg-info/top_level.txt
doc/source/conf.py
