Metadata-Version: 1.1
Name: arsenal-director
Version: 1.0.0.0b1.dev110
Summary: Ironic image caching service
Home-page: https://github.com/rackerlabs/arsenal
Author: Rackspace
Author-email: teeth-dev@lists.rackspace.com
License: Apache 2.0
Platform: UNKNOWN
Classifier: Environment :: OpenStack
Classifier: Intended Audience :: Information Technology
Classifier: Intended Audience :: System Administrators
Classifier: License :: OSI Approved :: Apache Software License
Classifier: Operating System :: POSIX :: Linux
Classifier: Programming Language :: Python
Classifier: Programming Language :: Python :: 2
Classifier: Programming Language :: Python :: 2.7
Classifier: Programming Language :: Python :: 2.6
Classifier: Development Status :: 4 - Beta
